[
   {
      "id":1,
      "name":"Sara",
      "phoneNum":"9999933333",
      "profilePic":"https://randomuser.me/api/portraits/women/1.jpg",
      "address":"Hyderabad India",
      "facebookLink":"https://facebook.com/testuser/",
      "instagramLink":"https://instagram.com/testuser/",
      "skills":[
         "Programming",
         "Photoshop"
      ],
      "projects":[
         {
            "name":"Project 1",
            "description":"Some description",
            "technologies":[
               "Html",
               "CSS",
               "JavaScript"
            ]
         }
      ]
   }
]
